jauth
