Metadata-Version: 2.1
Name: django-jauth
Version: 3.6.5
Summary: Simple OAuth2 login support for Django and Django REST Framework projects
Home-page: https://github.com/kajala/django-jauth
Author: Jani Kajala
Author-email: kajala@gmail.com
License: MIT licence, see LICENCE.txt
License-File: LICENSE.txt
Requires-Dist: Django>=3.1.0
Requires-Dist: django-extensions>=2.1.9
Requires-Dist: pytz>=2019.1
Requires-Dist: djangorestframework>=3.12
Requires-Dist: requests>=2.22.0
